setup.cfg
setup.py
ifv/__init__.py
ifv/http_api.py
ifv.egg-info/PKG-INFO
ifv.egg-info/SOURCES.txt
ifv.egg-info/dependency_links.txt
ifv.egg-info/pbr.json
ifv.egg-info/requires.txt
ifv.egg-info/top_level.txt