Metadata-Version: 1.1
Name: ifv
Version: 0.1.2
Summary: a simple common api client framework
Home-page: https://github.com/MrLYC/IFV
Author: MrLYC
Author-email: imyikong@gmail.com
License: MIT
Keywords: api,client,framework
Platform: UNKNOWN
Classifier: Development Status :: 3 - Alpha
Classifier: Intended Audience :: Developers
Classifier: Topic :: Software Development :: Build Tools
Classifier: License :: OSI Approved :: MIT License
Classifier: Programming Language :: Python :: 2
Classifier: Programming Language :: Python :: 2.7
Classifier: Programming Language :: Python :: 3
Classifier: Programming Language :: Python :: 3.3
Classifier: Programming Language :: Python :: 3.4
Classifier: Programming Language :: Python :: 3.5
Classifier: Programming Language :: Python :: 3.6
